pyrat/__init__.py
pyrat/base.py
pyrat/closure.py
pyrat/stats.py
pyrat/utils.py
pyrat_sdrabing-0.2.1.data/data/LICENSE
pyrat_sdrabing-0.2.1.dist-info/LICENSE
pyrat_sdrabing-0.2.1.dist-info/METADATA
pyrat_sdrabing-0.2.1.dist-info/WHEEL
pyrat_sdrabing-0.2.1.dist-info/top_level.txt
pyrat_sdrabing-0.2.1.dist-info/RECORD
