Metadata-Version: 2.1
Name: pyrat-sdrabing
Version: 0.2.1
Summary: R-like vectors and functions in Python.
Home-page: https://github.com/shanedrabing/pyrat
Author: Shane Drabing
Author-email: shane.drabing@gmail.com
License: UNKNOWN
Platform: UNKNOWN
Classifier: Programming Language :: Python :: 3
Classifier: License :: OSI Approved :: MIT License
License-File: LICENSE
